subdomains/__init__.py
subdomains/middleware.py
subdomains/models.py
subdomains/utils.py
subdomains/templatetags/__init__.py
subdomains/templatetags/subdomainurls.py
subdomains/tests/__init__.py
subdomains/tests/tests.py
subdomains/tests/views.py
subdomains/tests/urls/__init__.py
subdomains/tests/urls/api.py
subdomains/tests/urls/application.py
subdomains/tests/urls/default.py
subdomains/tests/urls/marketing.py
django21_subdomains-2.1.2.dist-info/LICENSE
django21_subdomains-2.1.2.dist-info/METADATA
django21_subdomains-2.1.2.dist-info/WHEEL
django21_subdomains-2.1.2.dist-info/top_level.txt
django21_subdomains-2.1.2.dist-info/RECORD
