Metadata-Version: 2.1
Name: django21-subdomains
Version: 2.1.2
Summary: Subdomain tools for the Django framework v2.1.x, including subdomain-based URL routing.
Home-page: https://github.com/kpavlovsky/django-subdomains
Author: Konstantin Pavlovsky
Author-email: konstantin.pavlovsky@gmail.com
License: MIT License
Platform: UNKNOWN
Requires-Dist: django (>2.1<2.2)
